spaghettree/__init__.py
spaghettree/__main__.py
spaghettree/adapters/__init__.py
spaghettree/adapters/io_wrapper.py
spaghettree/domain/__init__.py
spaghettree/domain/entities.py
spaghettree/domain/optimisation.py
spaghettree/domain/parsing.py
spaghettree/domain/processing.py
spaghettree/domain/visitors.py
spaghettree/logger/__init__.py
spaghettree-0.3.0.dist-info/WHEEL
spaghettree-0.3.0.dist-info/entry_points.txt
spaghettree-0.3.0.dist-info/METADATA
spaghettree-0.3.0.dist-info/RECORD
