Metadata-Version: 2.3
Name: spaghettree
Version: 0.3.0
Summary: Code that reorganises code
Author: ed cuss
Author-email: ed cuss <edcussmusic@gmail.com>
Requires-Dist: attrs>=25.1.0
Requires-Dist: black>=25.1.0
Requires-Dist: isort>=6.0.1
Requires-Dist: libcst>=1.6.0
Requires-Dist: numpy>=2.3.2
Requires-Dist: python-dotenv>=1.1.1
Requires-Dist: ruff>=0.12.9
Requires-Dist: tqdm>=4.67.1
Requires-Python: >=3.12
